FeiRays/Native.py
FeiRays/PyFeiRays.dll
FeiRays/Scene.py
FeiRays/__init__.py
FeiRays/libPyFeiRays.so
FeiRays/utils.py
FeiRays-0.0.6.dist-info/METADATA
FeiRays-0.0.6.dist-info/WHEEL
FeiRays-0.0.6.dist-info/top_level.txt
FeiRays-0.0.6.dist-info/RECORD
